{"cameraMode":{"drawMode":0,"name":"Shaded","section":"Shading Mode"},"sceneLighting":true,"audioPlay":false,"sceneViewState":{"showFog":true,"showMaterialUpdate":false,"showSkybox":true,"showFlares":true,"showImageEffects":true,"showParticleSystems":true},"in2DMode":false,"pivot":{"x":-1.0618828535079957,"y":1.6502165794372559,"z":-1.967543601989746},"rotation":{"x":0.18411092460155488,"y":-0.429970383644104,"z":0.09004270285367966,"w":0.8792929649353027},"size":11.095195770263672,"orthographic":false}